{
  "0": "other",
  "1": "chair",
  "2": "lamp",
  "3": "picture",
  "4": "sofa",
  "5": "table",
  "6": "bed",
  "7": "pillow",
  "8": "window",
  "9": "cabinet",
  "10": "mirror",
  "11": "floor mat",
  "12": "shelves",
  "13": "plant",
  "14": "dresser",
  "15": "vase",
  "16": "container",
  "17": "cart",
  "18": "clothes_rack",
  "19": "ladder",
  "20": "exercise_weight",
  "21": "fan",
  "22": "air_conditioner",
  "23": "mount",
  "24": "jar",
  "25": "clock",
  "26": "tent",
  "27": "electronic_device",
  "28": "battery_charger",
  "29": "cutlery",
  "30": "books",
  "31": "box",
  "32": "door",
  "33": "bottle",
  "34": "candle",
  "35": "cup",
  "36": "bin",
  "37": "display",
  "38": "tray",
  "39": "night stand",
  "40": "bookcase",
  "41": "refrigerator",
  "42": "camera",
  "43": "laptop",
  "44": "floor",
  "45": "walls",
  "46": "island",
  "47": "whiteboard",
  "48": "ceiling"
}